vocalhost.py
vocalhost-1.1.9.dist-info/METADATA
vocalhost-1.1.9.dist-info/WHEEL
vocalhost-1.1.9.dist-info/top_level.txt
vocalhost-1.1.9.dist-info/RECORD
