Metadata-Version: 2.1
Name: vocalhost
Version: 1.1.9
Summary: Localhost to Vocalhost, run functions from anywhere
Requires-Dist: websockets
Requires-Dist: certifi
Requires-Dist: requests
